LICENSE
README.rst
setup.py
pybrctl/__init__.py
pybrctl/pybrctl.py
pybrctl.egg-info/PKG-INFO
pybrctl.egg-info/SOURCES.txt
pybrctl.egg-info/dependency_links.txt
pybrctl.egg-info/top_level.txt