Metadata-Version: 2.1
Name: pybrctl
Version: 0.1.4
Summary: Python brctl wrapper
Home-page: https://github.com/udragon/pybrctl
Author: Ido Nahshon
Author-email: udragon@gmail.com
License: GPLv2
Keywords: brctl,bridge-utils
Classifier: License :: OSI Approved :: GNU General Public License v2 (GPLv2)
Classifier: Programming Language :: Python
Classifier: Operating System :: POSIX
Classifier: Programming Language :: Python :: 2.7
Classifier: Programming Language :: Python :: 3
License-File: LICENSE
